{
  "parent": "minecraft:recipes/root",
  "rewards": {
    "recipes": [
      "techemistry:gear_iron"
    ]
  },
  "criteria": {
    "material": {
      "trigger": "minecraft:inventory_changed",
      "conditions": {
        "items": [
          {
            "item": "minecraft:stone"
          }
        ]
      }
    },
    "has_the_recipe": {
      "trigger": "minecraft:recipe_unlocked",
      "conditions": {
        "recipe": "techemistry:gear_iron"
      }
    }
  },
  "requirements": [
    [
      "material",
      "has_the_recipe"
    ]
  ]
}